detect_test_pollution.py
detect_test_pollution-1.1.1.dist-info/LICENSE
detect_test_pollution-1.1.1.dist-info/METADATA
detect_test_pollution-1.1.1.dist-info/WHEEL
detect_test_pollution-1.1.1.dist-info/entry_points.txt
detect_test_pollution-1.1.1.dist-info/top_level.txt
detect_test_pollution-1.1.1.dist-info/RECORD
